StockExchange/__init__.py
StockExchange/nsestock.py
StockExchange-0.0.5.dist-info/LICENSE
StockExchange-0.0.5.dist-info/METADATA
StockExchange-0.0.5.dist-info/WHEEL
StockExchange-0.0.5.dist-info/top_level.txt
StockExchange-0.0.5.dist-info/RECORD
