Metadata-Version: 2.1
Name: StockExchange
Version: 0.0.5
Summary: Indian Stock Data Featch and Represent Graphical Format 
Author: Kaushal Zine
Author-email: <kaushalzine.it@gmail.com>
Keywords: python,nse,stock,sharemarket,Stock market,csv
Classifier: Development Status :: 1 - Planning
Classifier: Intended Audience :: Developers
Classifier: Programming Language :: Python :: 3
Classifier: Operating System :: Unix
Classifier: Operating System :: MacOS :: MacOS X
Classifier: Operating System :: Microsoft :: Windows
License-File: LICENSE
Requires-Dist: opencv-python
Requires-Dist: scikit-learn
Requires-Dist: numpy
Requires-Dist: pandas
Requires-Dist: matplotlib
Requires-Dist: datetime
Requires-Dist: requests
